{"data":[{"gid":"1215595920511909","created_at":"2026-06-10T12:08:48.367Z","created_by":{"gid":"1211147674764096","name":"Gocha Gafrindashvili"},"html_text":"<b><a href=\"https://app.asana.com/0/profile/1211144546600148\">Gocha Gafrindashvili</a></b> added this task to <a href=\"https://app.asana.com/1/45238840754660/project/1212521145936484\">Rumble Wallet</a>","text":"Gocha Gafrindashvili added this task to Rumble Wallet","type":"system","resource_subtype":"added_to_project"},{"gid":"1215596135387310","created_at":"2026-06-10T12:15:00.241Z","created_by":null,"html_text":"<b>Asana</b> changed Task Type to Task","text":"Asana changed Task Type to Task","type":"system","resource_subtype":"enum_custom_field_changed"},{"gid":"1215596161508589","created_at":"2026-06-10T12:15:38.752Z","created_by":{"gid":"1211147674764096","name":"Gocha Gafrindashvili"},"html_text":"<b><a href=\"https://app.asana.com/0/profile/1211144546600148\">Gocha Gafrindashvili</a></b> changed Support Type to Bug","text":"Gocha Gafrindashvili changed Support Type to Bug","type":"system","resource_subtype":"enum_custom_field_changed"},{"gid":"1215596107822902","created_at":"2026-06-10T12:15:41.539Z","created_by":{"gid":"1211147674764096","name":"Gocha Gafrindashvili"},"html_text":"<b><a href=\"https://app.asana.com/0/profile/1211144546600148\">Gocha Gafrindashvili</a></b> changed Task Type from Task to Bug","text":"Gocha Gafrindashvili changed Task Type from Task to Bug","type":"system","resource_subtype":"enum_custom_field_changed"},{"gid":"1215596064816389","created_at":"2026-06-10T12:15:43.071Z","created_by":{"gid":"1211147674764096","name":"Gocha Gafrindashvili"},"html_text":"<b><a href=\"https://app.asana.com/0/profile/1211144546600148\">Gocha Gafrindashvili</a></b> changed Stack to FE - frontend","text":"Gocha Gafrindashvili changed Stack to FE - frontend","type":"system","resource_subtype":"multi_enum_custom_field_changed"},{"gid":"1215596107832110","created_at":"2026-06-10T12:15:47.042Z","created_by":{"gid":"1211147674764096","name":"Gocha Gafrindashvili"},"html_text":"<b><a href=\"https://app.asana.com/0/profile/1211144546600148\">Gocha Gafrindashvili</a></b> changed Rumble Area to Transactions","text":"Gocha Gafrindashvili changed Rumble Area to Transactions","type":"system","resource_subtype":"multi_enum_custom_field_changed"},{"gid":"1215596123772827","created_at":"2026-06-10T12:15:52.636Z","created_by":{"gid":"1211147674764096","name":"Gocha Gafrindashvili"},"html_text":"<b><a href=\"https://app.asana.com/0/profile/1211144546600148\">Gocha Gafrindashvili</a></b> changed Priority to Critical (Bugs only)","text":"Gocha Gafrindashvili changed Priority to Critical (Bugs only)","type":"system","resource_subtype":"enum_custom_field_changed"},{"gid":"1215596108049329","created_at":"2026-06-10T12:16:07.078Z","created_by":{"gid":"1211147674764096","name":"Gocha Gafrindashvili"},"html_text":"<b><a href=\"https://app.asana.com/0/profile/1211144546600148\">Gocha Gafrindashvili</a></b> assigned to <b><a href=\"https://app.asana.com/0/profile/1212247759411844\">anton.kurdo@innowise.com</a></b>","text":"Gocha Gafrindashvili assigned to anton.kurdo@innowise.com","type":"system","resource_subtype":"assigned"},{"gid":"1215596108334553","created_at":"2026-06-10T12:17:45.540Z","created_by":{"gid":"1211147674764096","name":"Gocha Gafrindashvili"},"html_text":"<b><a href=\"https://app.asana.com/0/profile/1211144546600148\">Gocha Gafrindashvili</a></b> changed Sprint to Sprint 4","text":"Gocha Gafrindashvili changed Sprint to Sprint 4","type":"system","resource_subtype":"multi_enum_custom_field_changed"},{"gid":"1215594389679270","created_at":"2026-06-10T13:25:49.265Z","created_by":{"gid":"1211147674764096","name":"Gocha Gafrindashvili"},"html_text":"<body>As the issue appears for all users and across all networks, I am increasing the severity to <strong>Critical</strong>.\nReceive transactions were visible yesterday, so this seems to be a recent regression.\nI believe the backend side should be investigated as well.\ncc: <a href=\"https://app.asana.com/1/45238840754660/profile/1211860479278729\" data-asana-gid=\"1211860479278717\" data-asana-accessible=\"true\" data-asana-type=\"user\" data-asana-dynamic=\"true\">@Alex Atrash</a> <a href=\"https://app.asana.com/1/45238840754660/profile/1213406456321934\" data-asana-gid=\"1213406456321936\" data-asana-accessible=\"true\" data-asana-type=\"user\" data-asana-dynamic=\"true\">@Eddy WM</a></body>","is_pinned":false,"text":"As the issue appears for all users and across all networks, I am increasing the severity to Critical.\nReceive transactions were visible yesterday, so this seems to be a recent regression.\nI believe the backend side should be investigated as well.\ncc: https://app.asana.com/1/45238840754660/profile/1211860479278729 https://app.asana.com/1/45238840754660/profile/1213406456321934","type":"comment","resource_subtype":"comment_added"}]}