{"data":{"gid":"1213549645575555","assignee":{"gid":"1211860479278717","name":"Alex Atrash"},"assignee_status":"inbox","completed":false,"created_at":"2026-03-04T22:50:08.426Z","custom_fields":[{"gid":"1209456551951728","name":"WDK","display_value":"WDK-1255"},{"gid":"1209460639325103","name":"Priority","display_value":"High"},{"gid":"1209269077725448","name":"Estimated Points","display_value":null}],"due_on":null,"html_notes":"<body><pre>{job=&quot;pm2&quot;, level!=&quot;20&quot;} |= &quot;[DEP0170] DeprecationWarning: The URL mongodb&quot;\n\n{job=&quot;pm2&quot;, level!=&quot;20&quot;, service_name=~&quot;idx-xaut-arb-api.+&quot;} |= &quot;[DEP0170] DeprecationWarning: The URL mongodb&quot;</pre>PROD Grafana Loki Queries\n\nSTAGING EQUIVALENT:\n<pre>{agent=&quot;alloy&quot;, env=&quot;staging&quot;, level!=&quot;20&quot;} |= &quot;DeprecationWarning: The URL mongodb&quot;</pre>Note: an indexer needs to be restarted for the log to appear\n\nLeak DB password\n\n<pre>[DEP0170] DeprecationWarning: The URL mongodb://wallet:XXXXXX@....</pre>XXXXX will contain the leaked DB password\n\nPlease address this as this happened in production during a deployment and Rumble had to rotate the db password as people from the Tether team saw the prod db password\n\n===\n\nVigan suggested we use <a href=\"https://github.com/bitfinexcom/bfx-facs-db-mongo/tree/feature/mongodb-v6-driver\">https://github.com/bitfinexcom/bfx-facs-db-mongo/tree/feature/mongodb-v6-driver</a></body>","memberships":[{"project":{"gid":"1210540875949204","name":"WDK Indexer and Wallet Backends"},"section":{"gid":"1210540740718803","name":"PR MERGED + DEPLOYED TO DEV"}}],"modified_at":"2026-04-15T11:56:10.534Z","name":"Rumble - Bug - Security - Fix Mongo Deprecation Warning - Prod DB Password in Logs","notes":"{job=\"pm2\", level!=\"20\"} |= \"[DEP0170] DeprecationWarning: The URL mongodb\"\n\n{job=\"pm2\", level!=\"20\", service_name=~\"idx-xaut-arb-api.+\"} |= \"[DEP0170] DeprecationWarning: The URL mongodb\"\n\nPROD Grafana Loki Queries\n\nSTAGING EQUIVALENT:\n\n{agent=\"alloy\", env=\"staging\", level!=\"20\"} |= \"DeprecationWarning: The URL mongodb\"\n\nNote: an indexer needs to be restarted for the log to appear\n\nLeak DB password\n\n\n[DEP0170] DeprecationWarning: The URL mongodb://wallet:XXXXXX@....\n\nXXXXX will contain the leaked DB password\n\nPlease address this as this happened in production during a deployment and Rumble had to rotate the db password as people from the Tether team saw the prod db password\n\n===\n\nVigan suggested we use https://github.com/bitfinexcom/bfx-facs-db-mongo/tree/feature/mongodb-v6-driver","num_likes":0,"num_subtasks":0,"parent":null,"permalink_url":"https://app.asana.com/1/45238840754660/project/1210540875949204/task/1213549645575555","projects":[{"gid":"1210540875949204","name":"WDK Indexer and Wallet Backends"}],"tags":[]}}