{"data":{"gid":"1215461909208384","assignee":{"gid":"1211860479278717","name":"Alex Atrash"},"assignee_status":"inbox","completed":false,"created_at":"2026-06-05T15:16:03.668Z","custom_fields":[{"gid":"1212521145936507","name":"Priority","display_value":"High"},{"gid":"1214303648846174","name":"Sprint","display_value":"Sprint 3"},{"gid":"1210880937898809","name":"Rumble Area","display_value":null},{"gid":"1212560726842872","name":"Stack","display_value":null},{"gid":"1212640590108704","name":"Task Type","display_value":"Task"},{"gid":"1211628537010109","name":"RW","display_value":"RW-1862"},{"gid":"1211580506833725","name":"Support Type","display_value":null},{"gid":"1212523947271237","name":"Fix Version (FE)","display_value":null},{"gid":"1212863282854834","name":"Fix Version (BE)","display_value":null},{"gid":"1210732508806272","name":"Source","display_value":null}],"due_on":null,"html_notes":"<body>Implement what did with <a href=\"https://app.asana.com/0/search?q=WDK-1515&amp;searched_type=task&amp;child=1215216504545662&amp;f=true\" data-asana-gid=\"1215216504545662\" data-asana-accessible=\"true\" data-asana-type=\"task\" data-asana-dynamic=\"true\">✓ Investigate rumble prod ERR_WALLET_TRANSFER_RPC_FAIL (RPC client closed) requiring data-shard restarts</a> in <code>wdk-ork-wrk</code> and <code>rumble-ork-wrk</code>\n\nWhen a rant is sent through the wallet, the transaction completes on-chain and the recipient receives the funds, but nothing shows up in the chat. Seen on both prod and staging.\n\nReported by Mariia in Slack during mobile testing.\n\nExamples (all confirmed, nothing displayed in chat):\n\nProd\n- 0x1de8c852f240aE0a90ae6BeD9d32DF1AFd9C5cDE | 0.045 scudos ($0.20) | Jun 4, 16:04\n  <a href=\"https://etherscan.io/tx/0x73717270150ab968f5e909c5f2a4f93832b421cf46ffec4d21075ceb605ccaa5\">https://etherscan.io/tx/0x73717270150ab968f5e909c5f2a4f93832b421cf46ffec4d21075ceb605ccaa5</a>\n- 0x1de8c852f240aE0a90ae6BeD9d32DF1AFd9C5cDE | 0.3 USDt ($0.30) | Jun 4, 16:09\n  <a href=\"https://plasmascan.to/tx/0xa1c7498d44b98970871ac5e437a64820938b5b5ad8ca3a32a52d23df6a64d7fe\">https://plasmascan.to/tx/0xa1c7498d44b98970871ac5e437a64820938b5b5ad8ca3a32a52d23df6a64d7fe</a>\n\nStaging\n- 0x5430Ba7a62979b84B1894638c41776Ec7DC2EfE8 | 0.227 scudos ($1.00) | Jun 5, 09:17\n  <a href=\"https://etherscan.io/tx/0x424b06075da787533c5fad5c833b6f9608c13859c70318e1c89c7ee9fc30b027\">https://etherscan.io/tx/0x424b06075da787533c5fad5c833b6f9608c13859c70318e1c89c7ee9fc30b027</a>\n\nNeed to figure out why these rants are not appearing in the chat.\n\nSlack ref: <a href=\"https://tether-to.slack.com/archives/C094R63HQ64/p1780603661792139\">https://tether-to.slack.com/archives/C094R63HQ64/p1780603661792139</a>\n\n</body>","memberships":[{"project":{"gid":"1212521145936484","name":"Rumble Wallet"},"section":{"gid":"1212541709503050","name":"In-Progress"}}],"modified_at":"2026-06-12T10:59:43.312Z","name":"Implement Ork RPC Fix for Bug: Completed rant transactions not showing in chat","notes":"Implement what did with https://app.asana.com/0/search?q=WDK-1515&searched_type=task&child=1215216504545662&f=true in wdk-ork-wrk and rumble-ork-wrk\n\nWhen a rant is sent through the wallet, the transaction completes on-chain and the recipient receives the funds, but nothing shows up in the chat. Seen on both prod and staging.\n\nReported by Mariia in Slack during mobile testing.\n\nExamples (all confirmed, nothing displayed in chat):\n\nProd\n- 0x1de8c852f240aE0a90ae6BeD9d32DF1AFd9C5cDE | 0.045 scudos ($0.20) | Jun 4, 16:04\n  https://etherscan.io/tx/0x73717270150ab968f5e909c5f2a4f93832b421cf46ffec4d21075ceb605ccaa5\n- 0x1de8c852f240aE0a90ae6BeD9d32DF1AFd9C5cDE | 0.3 USDt ($0.30) | Jun 4, 16:09\n  https://plasmascan.to/tx/0xa1c7498d44b98970871ac5e437a64820938b5b5ad8ca3a32a52d23df6a64d7fe\n\nStaging\n- 0x5430Ba7a62979b84B1894638c41776Ec7DC2EfE8 | 0.227 scudos ($1.00) | Jun 5, 09:17\n  https://etherscan.io/tx/0x424b06075da787533c5fad5c833b6f9608c13859c70318e1c89c7ee9fc30b027\n\nNeed to figure out why these rants are not appearing in the chat.\n\nSlack ref: https://tether-to.slack.com/archives/C094R63HQ64/p1780603661792139\n\n","num_likes":0,"num_subtasks":1,"parent":null,"permalink_url":"https://app.asana.com/1/45238840754660/project/1212521145936484/task/1215461909208384","projects":[{"gid":"1212521145936484","name":"Rumble Wallet"}],"tags":[]}}